{"sections":{"main":{"type":"list-collections","blocks":{"a270ed26-037d-419b-a1dc-f9832022e55b":{"type":"collection","settings":{"collection":"costume-themes","custom_collection_image":"shopify:\/\/shop_images\/Kirsty_Team_Member_Pic.jpg"}},"77c29cad-a8dc-48b4-b275-b88ffdded0a6":{"type":"collection","settings":{"collection":"buy-accessories","custom_collection_image":"shopify:\/\/shop_images\/2019-08-17.jpg"}},"8ea23714-07b2-4954-a7f0-6b7a31a3c0f9":{"type":"collection","settings":{"collection":"buy-costumes","custom_collection_image":"shopify:\/\/shop_images\/custome_purchase.jpg"}},"4e9bf442-7ae9-4dd3-8503-2ae2064ca75e":{"type":"collection","settings":{"collection":"hire-costumes","custom_collection_image":"shopify:\/\/shop_images\/Fancy-That-Crows-Nest-CP-Trent-Van-der-jagt-1--1920x1080.jpg"}},"08f6d7f8-d2cb-4701-9719-8e4504d72993":{"type":"collection","settings":{"collection":"party-decor","custom_collection_image":"shopify:\/\/shop_images\/Fancy-That-Crows-Nest-CP-Trent-Van-der-jagt-3-1920x1080.jpg"}},"1584859e-c36d-430c-abd0-2c605baabd42":{"type":"collection","settings":{"collection":"balloons"}}},"block_order":["a270ed26-037d-419b-a1dc-f9832022e55b","77c29cad-a8dc-48b4-b275-b88ffdded0a6","8ea23714-07b2-4954-a7f0-6b7a31a3c0f9","4e9bf442-7ae9-4dd3-8503-2ae2064ca75e","08f6d7f8-d2cb-4701-9719-8e4504d72993","1584859e-c36d-430c-abd0-2c605baabd42"],"settings":{"wrapper":"full","layout":"grid","columns":3,"height":80,"text_size":100,"title":"Collections","button_text":"Shop All","button_style":"secondary","bg_color":"","text_color":"light","overlay_opacity":10,"enable_slider_mobile":true}},"0d1980f8-da5e-46dc-8280-3889beee6a7e":{"type":"section-newsletter","settings":{"flex_align":"align--middle-center","wrapper":"full","text_color":"text-light","title":"Join the Party!","text":"<p>Sign-up for exclusive offers, sales & event alerts.<\/p>","extra_fields":"","button_text":"","bg_color":"#e20d66","image_height":"three-fifty-height","image_position":"center-center","overlay_opacity":10}}},"order":["main","0d1980f8-da5e-46dc-8280-3889beee6a7e"]}